SolarEdge/SolarEdge.py
SolarEdge/__init__.py
SolarManager/SolarManager.py
SolarManager/__init__.py
SolarManager/Elements/__init__.py
SolarManager/Elements/enums.py
Sonnen/Sonnen.py
Sonnen/__init__.py
weconnect_solarmanager-0.5.6.data/data/SolarManager/Helper.py
weconnect_solarmanager-0.5.6.data/data/SolarManager/app.py
weconnect_solarmanager-0.5.6.data/data/SolarManager/config.txt
weconnect_solarmanager-0.5.6.data/data/SolarManager/init.py
weconnect_solarmanager-0.5.6.data/data/SolarManager/main.py
weconnect_solarmanager-0.5.6.data/data/SolarManager/logs/.gitkeep
weconnect_solarmanager-0.5.6.data/data/SolarManager/static/axios.min.js
weconnect_solarmanager-0.5.6.data/data/SolarManager/static/default.css
weconnect_solarmanager-0.5.6.data/data/SolarManager/static/jquery-3.6.4.js
weconnect_solarmanager-0.5.6.data/data/SolarManager/static/jquery-3.6.4.min.js
weconnect_solarmanager-0.5.6.data/data/SolarManager/static/manifest.json
weconnect_solarmanager-0.5.6.data/data/SolarManager/static/pushNotification.js
weconnect_solarmanager-0.5.6.data/data/SolarManager/static/serviceWorker.js
weconnect_solarmanager-0.5.6.data/data/SolarManager/static/images/favicon/icon-114.png
weconnect_solarmanager-0.5.6.data/data/SolarManager/static/images/favicon/icon-120.png
weconnect_solarmanager-0.5.6.data/data/SolarManager/static/images/favicon/icon-144.png
weconnect_solarmanager-0.5.6.data/data/SolarManager/static/images/favicon/icon-152.png
weconnect_solarmanager-0.5.6.data/data/SolarManager/static/images/favicon/icon-16.png
weconnect_solarmanager-0.5.6.data/data/SolarManager/static/images/favicon/icon-180.png
weconnect_solarmanager-0.5.6.data/data/SolarManager/static/images/favicon/icon-192.png
weconnect_solarmanager-0.5.6.data/data/SolarManager/static/images/favicon/icon-32.png
weconnect_solarmanager-0.5.6.data/data/SolarManager/static/images/favicon/icon-512.png
weconnect_solarmanager-0.5.6.data/data/SolarManager/static/images/favicon/icon-57.png
weconnect_solarmanager-0.5.6.dist-info/licenses/LICENSE
weconnect_solarmanager-0.5.6.dist-info/METADATA
weconnect_solarmanager-0.5.6.dist-info/WHEEL
weconnect_solarmanager-0.5.6.dist-info/top_level.txt
weconnect_solarmanager-0.5.6.dist-info/RECORD
