Metadata-Version: 2.4
Name: weconnect-solarmanager
Version: 0.5.6
Summary: With WeConnect-SolarManager you can automatically charge your Volkswagen ID car (e.g. ID.4) with solar electricity, even if your wallbox does not support this.
Home-page: https://github.com/wene37/WeConnect-SolarManager
Author: Thomas Werner
Project-URL: Bug Reports, https://github.com/wene37/WeConnect-SolarManager/issues
Project-URL: Source, https://github.com/wene37/WeConnect-SolarManager
Classifier: License :: OSI Approved :: MIT License
Requires-Python: >=3.7, <4
License-File: LICENSE
Requires-Dist: requests>=2.27.1
Requires-Dist: weconnect[Images]>=0.60.10
Requires-Dist: flask>=2.3.1
Requires-Dist: cryptography>=43.0.0
Requires-Dist: pywebpush>=2.0.0
Dynamic: author
Dynamic: classifier
Dynamic: description
Dynamic: description-content-type
Dynamic: home-page
Dynamic: license-file
Dynamic: project-url
Dynamic: requires-dist
Dynamic: requires-python
Dynamic: summary
